{
  "nodes": [
    {
      "id": "namcs",
      "label": "NAMCS HC Data",
      "detail": "9M+ annual FQHC visit records — the base for all probabilistic linkages to external datasets",
      "group": "hub",
      "who": "Researchers, epidemiologists, public health analysts, and policy makers studying FQHC populations",
      "what": "9M+ annual FQHC visit records with diagnoses, medications, demographics, and visit characteristics",
      "when": "2021 onwards — full-year EHR submissions; public files released 18–24 months after the collection year",
      "where": "95+ FQHCs across the U.S. Public files via NCHS; restricted files at FSRDC secure facilities",
      "why": "Fills a critical gap in FQHC-specific patient-centered outcomes research for underserved populations",
      "which": "Four access routes: dashboard, public file, restricted RDC file, and record linkage",
      "how": "Participating FQHCs submit HL7-formatted EHR encounter data; NCHS applies weighting and disclosure controls"
    },
    {
      "id": "hud",
      "label": "HUD Housing",
      "detail": "HUD administrative records on housing assistance — public housing, Section 8 vouchers, rental assistance",
      "group": "source",
      "who": "HUD-assisted households — public housing tenants, Section 8 voucher holders, rental assistance recipients",
      "what": "Housing assistance participation records: program type, duration, household characteristics",
      "when": "Linked data reflects housing status at time of FQHC visit; available ~2–3 years after encounter collection",
      "where": "Restricted access only — all analysis within FSRDC secure computing environments",
      "why": "Adds housing stability and affordability context invisible in the clinical encounter record",
      "which": "Public housing, Housing Choice Voucher (Section 8), and project-based rental assistance programs",
      "how": "Probabilistic match on name, date of birth, SSN, and residential address by NCHS data linking specialists"
    },
    {
      "id": "ndi",
      "label": "Death Index",
      "detail": "National Death Index — mortality status, date and cause of death for all U.S. deaths since 1979",
      "group": "source",
      "who": "Complete national mortality registry — all deaths in the United States regardless of location",
      "what": "Mortality status, date of death, underlying cause (ICD-10-CM), and contributing causes of death",
      "when": "NDI records lag 2–3 years; enables long-term survival analysis from 2021 FQHC encounters onward",
      "where": "Matching performed by NCHS specialists in secure environments; linked files only at FSRDC",
      "why": "Transforms cross-sectional visit data into longitudinal cohorts with definitive mortality ascertainment",
      "which": "All-cause mortality, cause-specific mortality, and preventable death analyses",
      "how": "Probabilistic match using name, SSN, date of birth, sex, race, and state of residence — >90% match rate"
    },
    {
      "id": "medicaid",
      "label": "Medicaid",
      "detail": "CMS Medicaid enrollment and claims files — insurance continuity and downstream service utilization",
      "group": "source",
      "who": "Medicaid-enrolled patients receiving care at participating FQHCs — a core FQHC patient population",
      "what": "Enrollment status, plan type, coverage periods, and claims for Medicaid-covered services",
      "when": "Linkage availability mirrors the encounter year with approximately a 2-year processing lag from CMS",
      "where": "CMS data accessed through FSRDC under a separate CMS data use agreement",
      "why": "Reveals how Medicaid coverage gaps and churning disrupt continuity of care at FQHCs",
      "which": "Fee-for-service and managed care Medicaid enrollment files and encounter claims",
      "how": "Medicaid ID or probabilistic match to CMS enrollment records using shared identifiers"
    },
    {
      "id": "housing_health",
      "label": "Housing Health",
      "detail": "Research enabled: How does housing stability affect FQHC utilization and chronic disease management?",
      "group": "output",
      "who": "Social determinants researchers studying housing policy impact on health outcomes at FQHCs",
      "what": "Studies linking housing assistance status to FQHC visit frequency and chronic disease management",
      "when": "Analysis possible once HUD linkage approval is granted — typically 3–6 months after application",
      "where": "All analyses within FSRDC secure computing environment; output reviewed before release",
      "why": "Quantifies the health return on investment in housing assistance programs for low-income populations",
      "which": "Cross-sectional and longitudinal housing-health association and program evaluation studies",
      "how": "Regression and propensity score models linking housing assistance status to care utilization"
    },
    {
      "id": "mortality",
      "label": "Mortality",
      "detail": "Research enabled: Which ambulatory care patterns predict 5-year mortality risk in FQHC populations?",
      "group": "output",
      "who": "Epidemiologists and health services researchers studying long-term outcomes after FQHC encounters",
      "what": "Survival analysis and cause-specific mortality studies following ambulatory care encounters",
      "when": "NDI linkage enables mortality follow-up from 2021 FQHC encounters through the most recent NDI year",
      "where": "All analyses within FSRDC secure environment; all output undergoes disclosure review before release",
      "why": "Evaluates care quality through the definitive outcome — whether patients survive following care",
      "which": "All-cause survival, cause-specific mortality, and preventable death rate studies",
      "how": "Kaplan-Meier curves, Cox proportional hazards models, and competing risks analyses"
    },
    {
      "id": "insurance",
      "label": "Insurance",
      "detail": "Research enabled: How does Medicaid churning affect continuity of FQHC care and health outcomes?",
      "group": "output",
      "who": "Health economists and policy analysts studying Medicaid coverage effects on FQHC care continuity",
      "what": "Studies of insurance continuity, churning effects, and downstream healthcare utilization patterns",
      "when": "Enabled once Medicaid linkage is approved; coverage gaps can be traced around each FQHC encounter",
      "where": "FSRDC secure environment; CMS data use agreement required in addition to FSRDC approval",
      "why": "Reveals how coverage gaps disrupt care continuity and worsen health outcomes for FQHC patients",
      "which": "Coverage continuity, churning frequency, and utilization during and after Medicaid coverage gaps",
      "how": "Longitudinal analysis linking enrollment periods to FQHC visit patterns and downstream outcomes"
    },
    {
      "id": "sdoh",
      "label": "Combined SDH",
      "detail": "Research enabled: How do housing instability and coverage gaps compound to drive the deepest health inequities?",
      "group": "output",
      "who": "Health equity researchers examining compound social disadvantage and intersecting risk factors",
      "what": "Multi-linkage studies combining housing, mortality, and insurance context around FQHC encounters",
      "when": "Requires simultaneous approval for HUD, NDI, and/or Medicaid linkages — complex multi-step application",
      "where": "Complex multi-file linkage accessed only through FSRDC; additional coordination with NCHS required",
      "why": "Reveals how compounding social disadvantages drive the deepest and most persistent health inequities",
      "which": "Intersectional analyses combining housing, insurance, and mortality for health equity research",
      "how": "Multi-level modeling and mediation analysis across linked social determinants and clinical encounter data"
    }
  ],
  "links": [
    {
      "source": "namcs",
      "target": "hud",
      "type": "partOf",
      "relationship": "Probabilistic match",
      "description": "NAMCS patient identifiers matched to HUD housing assistance records via probabilistic algorithms at NCHS"
    },
    {
      "source": "namcs",
      "target": "ndi",
      "type": "partOf",
      "relationship": "Probabilistic match",
      "description": "NAMCS patient identifiers matched to NDI mortality records — match rates exceed 90% for adults with complete SSN"
    },
    {
      "source": "namcs",
      "target": "medicaid",
      "type": "partOf",
      "relationship": "Enrollment linkage",
      "description": "NAMCS patient identifiers linked to CMS Medicaid enrollment files via Medicaid ID or probabilistic match"
    },
    {
      "source": "hud",
      "target": "housing_health",
      "type": "contains",
      "relationship": "Enables",
      "description": "HUD linkage enables studies of housing assistance impact on FQHC utilization and chronic disease management"
    },
    {
      "source": "ndi",
      "target": "mortality",
      "type": "contains",
      "relationship": "Enables",
      "description": "NDI linkage enables survival analysis and cause-of-death studies following ambulatory care encounters"
    },
    {
      "source": "medicaid",
      "target": "insurance",
      "type": "contains",
      "relationship": "Enables",
      "description": "Medicaid linkage enables studies of coverage continuity, churning effects, and downstream service use"
    },
    {
      "source": "hud",
      "target": "sdoh",
      "type": "contains",
      "relationship": "Combines for",
      "description": "Combined HUD + NDI + Medicaid linkages reveal how social determinants compound to drive health disparities"
    },
    {
      "source": "ndi",
      "target": "sdoh",
      "type": "contains",
      "relationship": "Combines for",
      "description": "Mortality outcomes contextualized by housing and insurance status reveal compound disadvantage in FQHC populations"
    }
  ]
}
